garm-0.3.4.data/purelib/garm/__init__.py
garm-0.3.4.data/purelib/garm/garm.py
garm-0.3.4.data/purelib/garm/lib/libcgarm.so
garm-0.3.4.data/purelib/garm/lib/libgarm.so
garm-0.3.4.dist-info/LICENSE
garm-0.3.4.dist-info/METADATA
garm-0.3.4.dist-info/WHEEL
garm-0.3.4.dist-info/top_level.txt
garm-0.3.4.dist-info/RECORD
