Metadata-Version: 2.1
Name: garm
Version: 0.3.4
Summary: Library to generate 3D animation (glTF,USD) files from robot model in URDF
Home-page: UNKNOWN
Author: Masanobu Koga
Author-email: koga@ics.kyutech.ac.jp
License: UNKNOWN
Keywords: URDF,ROS,robot,glTF,USD
Platform: UNKNOWN
Classifier: Programming Language :: Python :: 3
Classifier: License :: OSI Approved :: Apache Software License
Classifier: Operating System :: POSIX :: Linux
Classifier: Operating System :: Microsoft :: Windows
Classifier: Operating System :: MacOS
